<?xml version="1.0"?>

<markers>
<marker name="0" type="1" lat="32.77186" lng="-115.68256"/>
<marker name="1" type="1" lat="33.96666" lng="-117.91692"/>
<marker name="2" type="1" lat="33.3467" lng="-116.26233"/>
<marker name="3" type="1" lat="33.39874" lng="-116.7485"/>
<marker name="4" type="1" lat="33.13223" lng="-116.29082"/>
<marker name="5" type="1" lat="33.93608" lng="-117.54746"/>
<marker name="6" type="1" lat="33.2079" lng="-115.9247"/>
<marker name="7" type="1" lat="32.43067" lng="-116.94404"/>
<marker name="8" type="1" lat="34.35156" lng="-116.85147"/>
<marker name="9" type="1" lat="34.02291" lng="-117.60287"/>
<marker name="10" type="1" lat="33.24102" lng="-116.44392"/>
<marker name="11" type="1" lat="32.31183" lng="-116.16318"/>
<marker name="12" type="1" lat="34.28666" lng="-117.14757"/>
<marker name="13" type="1" lat="34.04813" lng="-117.07206"/>
<marker name="14" type="1" lat="33.85601" lng="-117.40839"/>
<marker name="15" type="1" lat="33.62227" lng="-115.93509"/>
<marker name="16" type="1" lat="32.75572" lng="-115.78931"/>
<marker name="17" type="1" lat="33.66209" lng="-117.2176"/>
<marker name="18" type="1" lat="33.70109" lng="-116.57188"/>
<marker name="19" type="1" lat="32.81497" lng="-116.18235"/>
<marker name="20" type="1" lat="32.98299" lng="-116.30709"/>
<marker name="21" type="1" lat="32.93589" lng="-115.26904"/>
<marker name="22" type="1" lat="34.00102" lng="-117.21991"/>
<marker name="23" type="1" lat="33.98449" lng="-116.99424"/>
<marker name="24" type="1" lat="32.67113" lng="-116.8934"/>
<marker name="25" type="1" lat="34.40353" lng="-116.57253"/>
<marker name="26" type="1" lat="33.48298" lng="-116.56601"/>
<marker name="27" type="1" lat="33.60796" lng="-115.99635"/>
<marker name="28" type="1" lat="33.30541" lng="-116.2748"/>
<marker name="29" type="1" lat="33.55313" lng="-116.28703"/>
<marker name="30" type="1" lat="32.64833" lng="-115.34073"/>
<marker name="31" type="1" lat="33.00997" lng="-116.21062"/>
<marker name="32" type="1" lat="33.8756" lng="-117.24183"/>
<marker name="33" type="1" lat="32.97927" lng="-115.959"/>
<marker name="34" type="1" lat="33.81172" lng="-116.92139"/>
<marker name="35" type="1" lat="32.83816" lng="-116.70489"/>
<marker name="36" type="1" lat="33.14011" lng="-116.95358"/>
<marker name="37" type="1" lat="34.23009" lng="-116.67163"/>
<marker name="38" type="1" lat="33.77054" lng="-117.34849"/>
</markers>

