<?xml version="1.0"?>

<markers>
<marker name="1" type="1" lat="35.12440157992043" lng="-82.781982421875"/>
<marker name="2" type="1" lat="34.876918445772084" lng="-82.781982421875"/>
<marker name="3" type="1" lat="34.845366931840985" lng="-82.4139404296875"/>
<marker name="4" type="1" lat="34.97600151317588" lng="-82.1063232421875"/>
<marker name="5" type="1" lat="35.17829835200121" lng="-82.1063232421875"/>
<marker name="6" type="1" lat="35.29943548054545" lng="-82.3699951171875"/>
<marker name="7" type="1" lat="35.29943548054545" lng="-82.6007080078125"/>
<marker name="8" type="1" lat="35.137879119634185" lng="-82.298583984375"/>
<marker name="9" type="1" lat="34.93097858831627" lng="-82.2821044921875"/>
<marker name="10" type="1" lat="34.858890491257796" lng="-82.6007080078125"/>
<marker name="11" type="1" lat="34.9895035675793" lng="-82.79296875"/>
<marker name="12" type="1" lat="35.263561862152095" lng="-82.7215576171875"/>
<marker name="13" type="1" lat="35.24561909420681" lng="-82.2216796875"/>
<marker name="14" type="1" lat="35.24561909420681" lng="-82.4139404296875"/>
<marker name="15" type="1" lat="35.24561909420681" lng="-82.606201171875"/>
<marker name="16" type="1" lat="35.08845057036537" lng="-82.672119140625"/>
<marker name="17" type="1" lat="35.02999636902565" lng="-82.342529296875"/>
<marker name="18" type="1" lat="35.05698043137265" lng="-82.2381591796875"/>
</markers>

