{	"simulation":{"parameters":{"ID":"200","sim_conn":"conn","cuttime":"30","start_time":"1378297891","debug":"false","sim_seed":"","perfect":"false","sim_name": "M6.5 - 29km SSE of Blenheim, New Zealand","sim_desc": "hello\
sd","map": {"location": { "lat":"-38.126136565761", "lng":"175.70705908203126"},"zoom" : "3","mapType" : "hybrid"}},"earthquakes":[{"ID":"3","magnitude":"6.5","time":"10","swaveSpeed":"10","depth":"10","location":{"lat":"-41.767","lng":"174.06100000000004"}}],"areas":[],"markers":[{"ID":"undefined", "type":"1","location":{"lat":"-41.52708581365464","lng":"174.05648231506348"}},{"ID":"undefined", "type":"1","location":{"lat":"-41.559976772581706","lng":"174.00155067443848"}},{"ID":"undefined", "type":"1","location":{"lat":"-41.570251766098934","lng":"173.91366004943848"}},{"ID":"undefined", "type":"1","location":{"lat":"-41.512690758458575","lng":"173.85048866271973"}},{"ID":"undefined", "type":"1","location":{"lat":"-41.46331197668623","lng":"173.89718055725098"}},{"ID":"undefined", "type":"1","location":{"lat":"-41.46742831254424","lng":"173.98507118225098"}},{"ID":"undefined", "type":"1","location":{"lat":"-42.01665183556823","lng":"173.71315956115723"}},{"ID":"undefined", "type":"1","location":{"lat":"-42.01461122881795","lng":"173.59780311584473"}},{"ID":"undefined", "type":"1","location":{"lat":"-42.09210825254958","lng":"173.64449501037598"}},{"ID":"undefined", "type":"1","location":{"lat":"-42.06764572379527","lng":"173.73513221740723"}},{"ID":"undefined", "type":"1","location":{"lat":"-41.31494988250964","lng":"174.77059364318848"}},{"ID":"undefined", "type":"1","location":{"lat":"-41.244772343082076","lng":"174.76510047912598"}},{"ID":"undefined", "type":"1","location":{"lat":"-41.286062387498255","lng":"174.67446327209473"}},{"ID":"undefined", "type":"1","location":{"lat":"-41.549700145132725","lng":"173.58681678771973"}},{"ID":"undefined", "type":"1","location":{"lat":"-41.58257960143034","lng":"175.29519081115723"}}],"SensorTypes":[{"ID":"1","on_frac":"1","conn_frac":"1","act_frac":"1","os_name":"Microsoft Windows XP","num_cpus":"2","proc_make":"Genuine Intel","proc_model":"Pentium 4","flops":"1411554690.0357","iops":"3164629924.34267","membandw":"500000000","c_time":"1","mean_conn":"86400","std_conn":"3600","max_rpd":"24","success_rate":"98","error_rate":"2","flase_trig_rate":"","trig_lower_bound":"0.098","trig_upper_bound":"0.196","trig_prob":"0.5"}]	}}